nltools/__init__.py
nltools/tokenizer.py
nltools/asr.py
nltools/threadpool.py
nltools/pulseplayer.py
nltools/sequiturclient.py
nltools/macro_engine.py
nltools/vad.py
nltools/misc.py
nltools/pulserecorder.py
nltools/phonetics.py
nltools/tts.py
py_nltools-0.5.0.dist-info/top_level.txt
py_nltools-0.5.0.dist-info/METADATA
py_nltools-0.5.0.dist-info/DESCRIPTION.rst
py_nltools-0.5.0.dist-info/metadata.json
py_nltools-0.5.0.dist-info/WHEEL
py_nltools-0.5.0.dist-info/RECORD
