Metadata-Version: 2.0
Name: py-nltools
Version: 0.5.0
Summary: A collection of basic python modules for spoken natural language processing
Home-page: https://github.com/gooofy/py-nltools
Author: Guenter Bartsch
Author-email: guenter@zamia.org
License: Apache
Keywords: natural language processing tokenizer nlp tts asr speech synthesis recognition
Platform: UNKNOWN
Classifier: Operating System :: POSIX :: Linux
Classifier: License :: OSI Approved :: Apache Software License
Classifier: Programming Language :: Python :: 2
Classifier: Programming Language :: Python :: 2.7
Classifier: Programming Language :: Python :: 3
Classifier: Programming Language :: Python :: 3.5
Classifier: Intended Audience :: Developers
Classifier: Topic :: Multimedia :: Sound/Audio :: Speech
Classifier: Topic :: Scientific/Engineering :: Artificial Intelligence
Requires-Dist: num2words
Requires-Dist: py-marytts
Requires-Dist: py-picotts
Requires-Dist: py-espeak-ng
Requires-Dist: py-kaldi-asr
Requires-Dist: numpy
Requires-Dist: webrtcvad
Requires-Dist: setproctitle
